temp/processor/single.v
`include "alu.v"


module top (
	input wire clk,
	input wire reset,
	output wire [31:0] WriteData,
	output wire [31:0] DataAdr,
	output wire MemWrite
);
	wire [31:0] PC;
	wire [31:0] Instr;
	wire [31:0] ReadData;
	arm arm(
		.clk(clk),
		.reset(reset),
		.PC(PC),
		.Instr(Instr),
		.MemWrite(MemWrite),
		.ALUResult(DataAdr),
		.WriteData(WriteData),
		.ReadData(ReadData)
	);
	imem imem(
		.a(PC),
		.rd(Instr)
	);
	
	dmem dmem(
		.clk(clk),
		.we(MemWrite),
		.a(DataAdr),
		.wd(WriteData),
		.rd(ReadData)
	);
endmodule
module dmem (
	input wire clk,
	input wire we,
	input wire [31:0] a,
	input wire [31:0] wd,
	output wire [31:0] rd
);
	
	reg [31:0] RAM [63:0];
	assign rd = RAM[a[31:2]];

	always @(posedge clk) begin
		if (we) begin
			RAM[a[31:2]] <= wd;
		end
	end
endmodule
module imem (
	input wire [31:0] a,
	output wire [31:0] rd
);

	reg [31:0] RAM [22:0];
	initial begin 
		$readmemh("memfile.dat", RAM);
	end

	assign rd = RAM[a[31:2]];
endmodule
module arm (
	input wire clk,
	input wire reset,
	output wire [31:0] PC,
	input wire [31:0] Instr,
	output wire MemWrite,
	output wire [31:0] ALUResult,
	output wire [31:0] WriteData,
	input wire [31:0] ReadData
);
	wire [3:0] ALUFlags;
	wire RegWrite;
	wire ALUSrc;
	wire MemtoReg;
	wire PCSrc;
	wire [1:0] RegSrc;
	wire [1:0] ImmSrc;
	wire [2:0] ALUControl;
	controller c(
		.clk(clk),
		.reset(reset),
		.Instr(Instr[31:12]),
		.ALUFlags(ALUFlags),
		.RegSrc(RegSrc),
		.RegWrite(RegWrite),
		.ImmSrc(ImmSrc),
		.ALUSrc(ALUSrc),
		.ALUControl(ALUControl),
		.MemWrite(MemWrite),
		.MemtoReg(MemtoReg),
		.PCSrc(PCSrc)
	);
	datapath dp(
		.clk(clk),
		.reset(reset),
		.RegSrc(RegSrc),
		.RegWrite(RegWrite),
		.ImmSrc(ImmSrc),
		.ALUSrc(ALUSrc),
		.ALUControl(ALUControl),
		.MemtoReg(MemtoReg),
		.PCSrc(PCSrc),
		.ALUFlags(ALUFlags),
		.PC(PC),
		.Instr(Instr),
		.ALUResult(ALUResult),
		.WriteData(WriteData),
		.ReadData(ReadData)
	);
endmodule

module controller (
	input wire clk,
	input wire reset,
	input wire [31:12] Instr,
	input wire [3:0] ALUFlags,
	output wire [1:0] RegSrc,
	output wire RegWrite,
	output wire [1:0] ImmSrc,
	output wire ALUSrc,
	output wire [2:0] ALUControl,
	output wire MemWrite,
	output wire MemtoReg,
	output wire PCSrc
);
	wire [1:0] FlagW;
	wire PCS;
	wire RegW;
	wire MemW;
	decode dec(
		.Op(Instr[27:26]),
		.Funct(Instr[25:20]),
		.Rd(Instr[15:12]),
		.FlagW(FlagW),
		.PCS(PCS),
		.RegW(RegW),
		.MemW(MemW),
		.MemtoReg(MemtoReg),
		.ALUSrc(ALUSrc),
		.ImmSrc(ImmSrc),
		.RegSrc(RegSrc),
		.ALUControl(ALUControl)
	);
	condlogic cl(
		.clk(clk),
		.reset(reset),
		.Cond(Instr[31:28]),
		.ALUFlags(ALUFlags),
		.FlagW(FlagW),
		.PCS(PCS),
		.RegW(RegW),
		.MemW(MemW),
		.PCSrc(PCSrc),
		.RegWrite(RegWrite),
		.MemWrite(MemWrite)
	);
endmodule

module decode (
	input wire [1:0] Op,
	input wire [5:0] Funct,
	input wire [3:0] Rd,
	output reg [1:0] FlagW,
	output wire PCS,
	output wire RegW,
	output wire MemW,
	output wire MemtoReg,
	output wire ALUSrc,
	output wire [1:0] ImmSrc,
	output wire [1:0] RegSrc,
	output reg [2:0] ALUControl
);
	reg [9:0] controls;
	wire Branch;
	wire ALUOp;
	always @(*) begin
		casex (Op)
			2'b00:
				if (Funct[5])
					controls = 10'b0000101001;
				else
					controls = 10'b0000001001;
			2'b01:
				if (Funct[0])
					controls = 10'b0001111000;
				else
					controls = 10'b1001110100;
			2'b10: controls = 10'b0110100010;
			default: controls = 10'bxxxxxxxxxx;
		endcase
	end
	assign {RegSrc, ImmSrc, ALUSrc, MemtoReg, RegW, MemW, Branch, ALUOp} = controls;
	always @(*) begin
		if (ALUOp) begin
			case (Funct[4:1])
				4'b0100: ALUControl = 2'b00;
				4'b0010: ALUControl = 2'b01;
				4'b0000: ALUControl = 2'b10;
				4'b1100: ALUControl = 2'b11;
				default: ALUControl = 2'bxx;
			endcase
			FlagW[1] = Funct[0];
			FlagW[0] = Funct[0] & ((ALUControl == 2'b00) | (ALUControl == 2'b01));
		end
		else begin
			ALUControl = 2'b00;
			FlagW = 2'b00;
		end
	end
	assign PCS = ((Rd == 4'b1111) & RegW) | Branch;
endmodule

module condlogic (
	input wire clk,
	input wire reset,
	input wire [3:0] Cond,
	input wire [3:0] ALUFlags,
	input wire [1:0] FlagW,
	input wire PCS,
	input wire RegW,
	input wire MemW,
	output wire PCSrc,
	output wire RegWrite,
	output wire MemWrite
);
	wire [1:0] FlagWrite;
	wire [3:0] Flags;
	wire CondEx;
	flopenr #(2) flagreg1(
		.clk(clk),
		.reset(reset),
		.en(FlagWrite[1]),
		.d(ALUFlags[3:2]),
		.q(Flags[3:2])
	);
	flopenr #(2) flagreg0(
		.clk(clk),
		.reset(reset),
		.en(FlagWrite[0]),
		.d(ALUFlags[1:0]),
		.q(Flags[1:0])
	);
	condcheck cc(
		.Cond(Cond),
		.Flags(Flags),
		.CondEx(CondEx)
	);
	assign FlagWrite = FlagW & {2 {CondEx}};
	assign RegWrite = RegW & CondEx;
	assign MemWrite = MemW & CondEx;
	assign PCSrc = PCS & CondEx;
endmodule
module condcheck (
	input wire [3:0] Cond,
	input wire [3:0] Flags,
	output reg CondEx
);
	wire neg;
	wire zero;
	wire carry;
	wire overflow;
	wire ge;
	assign {neg, zero, carry, overflow} = Flags;
	assign ge = neg == overflow;
	always @(*)
		case (Cond)
			4'b0000: CondEx = zero;
			4'b0001: CondEx = ~zero;
			4'b0010: CondEx = carry;
			4'b0011: CondEx = ~carry;
			4'b0100: CondEx = neg;
			4'b0101: CondEx = ~neg;
			4'b0110: CondEx = overflow;
			4'b0111: CondEx = ~overflow;
			4'b1000: CondEx = carry & ~zero;
			4'b1001: CondEx = ~(carry & ~zero);
			4'b1010: CondEx = ge;
			4'b1011: CondEx = ~ge;
			4'b1100: CondEx = ~zero & ge;
			4'b1101: CondEx = ~(~zero & ge);
			4'b1110: CondEx = 1'b1;
			default: CondEx = 1'bx;
		endcase
endmodule
module datapath (
	input wire clk,
	input wire reset,
	input wire [1:0] RegSrc,
	input wire RegWrite,
	input wire [1:0] ImmSrc,
	input wire ALUSrc,
	input wire [2:0] ALUControl,
	input wire MemtoReg,
	input wire PCSrc,
	output wire [3:0] ALUFlags,
	output wire [31:0] PC,
	input wire [31:0] Instr,
	output wire [31:0] ALUResult,
	output wire [31:0] WriteData,
	input wire [31:0] ReadData
);
	wire [31:0] PCNext;
	wire [31:0] PCPlus4;
	wire [31:0] PCPlus8;
	wire [31:0] ExtImm;
	wire [31:0] SrcA;
	wire [31:0] SrcB;
	wire [31:0] Result;
	wire [3:0] RA1;
	wire [3:0] RA2;
	mux2 #(32) pcmux(
		.d0(PCPlus4),
		.d1(Result),
		.s(PCSrc),
		.y(PCNext)
	);
	flopr #(32) pcreg(
		.clk(clk),
		.reset(reset),
		.d(PCNext),
		.q(PC)
	);
	adder #(32) pcadd1(
		.a(PC),
		.b(32'b100),
		.y(PCPlus4)
	);
	adder #(32) pcadd2(
		.a(PCPlus4),
		.b(32'b100),
		.y(PCPlus8)
	);
	mux2 #(4) ra1mux(
		.d0(Instr[19:16]),
		.d1(4'b1111),
		.s(RegSrc[0]),
		.y(RA1)
	);
	mux2 #(4) ra2mux(
		.d0(Instr[3:0]),
		.d1(Instr[15:12]),
		.s(RegSrc[1]),
		.y(RA2)
	);
	regfile rf(
		.clk(clk),
		.we3(RegWrite),
		.ra1(RA1),
		.ra2(RA2),
		.wa3(Instr[15:12]),
		.wd3(Result),
		.r15(PCPlus8),
		.rd1(SrcA),
		.rd2(WriteData)
	);
	mux2 #(32) resmux(
		.d0(ALUResult),
		.d1(ReadData),
		.s(MemtoReg),
		.y(Result)
	);
	extend ext(
		.Instr(Instr[23:0]),
		.ImmSrc(ImmSrc),
		.ExtImm(ExtImm)
	);
	mux2 #(32) srcbmux(
		.d0(WriteData),
		.d1(ExtImm),
		.s(ALUSrc),
		.y(SrcB)
	);
	alu alu(
		.A(SrcA),
		.B(SrcB),
		.ALUControl(ALUControl),
		.Result(ALUResult),
		.ALUFlags(ALUFlags)
	);
	
endmodule
module regfile (
	input wire clk,
	input wire we3,
	input wire [3:0] ra1,
	input wire [3:0] ra2,
	input wire [3:0] wa3,
	input wire [31:0] wd3,
	input wire [31:0] r15,
	output wire [31:0] rd1,
	output wire [31:0] rd2
);

	reg [31:0] rf [14:0];
	always @(posedge clk) begin
		if (we3)
			rf[wa3] <= wd3;
	end
	assign rd1 = (ra1 == 4'b1111 ? r15 : rf[ra1]);
	assign rd2 = (ra2 == 4'b1111 ? r15 : rf[ra2]);
endmodule
module extend (
	input wire [23:0] Instr,
	input wire [1:0] ImmSrc,
	output reg [31:0] ExtImm
);
	always @(*) begin
		case (ImmSrc)
			2'b00: ExtImm = {24'b000000000000000000000000, Instr[7:0]};
			2'b01: ExtImm = {20'b00000000000000000000, Instr[11:0]};
			2'b10: ExtImm = {{6 {Instr[23]}}, Instr[23:0], 2'b00};
			default: ExtImm = 32'bxxxxxxxxxxxxxxxxxxxxxxxxxxxxxxxx;
		endcase
	end
endmodule
module adder (
	a,
	b,
	y
);
	parameter WIDTH = 8;
	input wire [WIDTH - 1:0] a;
	input wire [WIDTH - 1:0] b;
	output wire [WIDTH - 1:0] y;
	assign y = a + b;
endmodule
module flopenr (
	clk,
	reset,
	en,
	d,
	q
);
	parameter WIDTH = 8;
	input wire clk;
	input wire reset;
	input wire en;
	input wire [WIDTH - 1:0] d;
	output reg [WIDTH - 1:0] q;
	always @(posedge clk or posedge reset) begin
		if (reset)
			q <= 0;
		else if (en)
			q <= d;
	end
endmodule
module flopr (
	clk,
	reset,
	d,
	q
);
	parameter WIDTH = 8;
	input wire clk;
	input wire reset;
	input wire [WIDTH - 1:0] d;
	output reg [WIDTH - 1:0] q;
	always @(posedge clk or posedge reset) begin
		if (reset)
			q <= 0;
		else
			q <= d;
	end
endmodule
module mux2 (
	d0,
	d1,
	s,
	y
);
	parameter WIDTH = 8;
	input wire [WIDTH - 1:0] d0;
	input wire [WIDTH - 1:0] d1;
	input wire s;
	output wire [WIDTH - 1:0] y;
	assign y = (s ? d1 : d0);
endmodule

ALU.v
module alu (
	input [2:0] ALUControl, input [31:0] A, input [31:0] B,  // Declaration ofinputs and ALUControl signal, A & B support 32 bits
	output [3:0] ALUFlags, output reg [31:0] Result, output reg [31:0] ResultExtra // Declaration of module outputs 
);
	wire [31:0] mux2_1; // Wire to hold the output of the mux2:1 
	wire [32:0] Sum; // Wire that will hold the sum of A and B if it is required
	wire Overflow, Carry,Negative, Zero; // Wires that hold each ALU Flag
    wire [63:0] Product;
	wire [31:0] FactorA, FactorB;

	assign mux2_1 = (ALUControl[0]==0)? B: ~B; // MUX 2:1 simplification using the conditional operator
	assign Sum = A+mux2_1+ALUControl[0]; // Definition of the ADDER module
	
	assign FactorA = (ALUControl[2]&ALUControl[1]&~ALUControl[0])?(A[31]?~A+1:A):A;
	assign FactorB = (ALUControl[2]&ALUControl[1]&~ALUControl[0])?(B[31]?~B+1:B):B;

	assign Product = (ALUControl[2]&ALUControl[1]&~ALUControl[0])?((A[31]^B[31])?~(FactorA*FactorB)+1:FactorA*FactorB):FactorA*FactorB;
	// MUX 4:1 simplification using the CASE keyword & syntax
	always @(*) begin
		casex (ALUControl)
			3'b00?: {ResultExtra, Result} = {32'b0, Sum[31:0]}; // ALUControl signal 00/01 means ADD and SUB, so either way A and B will be added
			3'b010: {ResultExtra, Result} = {32'b0 , A & B}; // ALUControl signal 10 means AND
			3'b011: {ResultExtra, Result} = {32'b0, A | B}; // ALUControl signal 01 means OR
            //MUL: 100
            //SMULL: 110
            //UMULL: 111 voy a hacer push y cortar el live share 
            3'b1??: {ResultExtra, Result} = Product;
		endcase
	end

  	assign Overflow = ~(ALUControl[0]^A[31]^B[31]) & (Sum[31]^A[31]) & ~ALUControl[1]; // Overflow flag wire
	assign Zero = (32'b0 == Result) & (32'b0 == ResultExtra); // If every bit is 0, then the zero result flag will activate
	assign Negative = ALUControl[2] ? ResultExtra[31] : Result[31]; // If the first bit from the left is 1,  the result will be negative
	assign Carry = ~ALUControl[1] & Sum[32]; // Carry will be 1 if the ALUControl signal is addition or subtraction and if the 1st bit from the left bit is 1
	assign ALUFlags = {Negative, Zero, Carry, Overflow}; // We group each bit-flag to the ALUFlags output    

endmodule

Singlecycle/single_tb.v
`include "single.v"
module testbench;
	reg clk;
	reg reset;
	wire [31:0] WriteData;
	wire [31:0] DataAdr;
	wire MemWrite;
	top dut(
		.clk(clk),
		.reset(reset),
		.WriteData(WriteData),
		.DataAdr(DataAdr),
		.MemWrite(MemWrite)
	);
	initial begin
		reset <= 1;
		#(22);
		reset <= 0;
	end
	always begin
		clk <= 1;
		#(5);
		clk <= 0;
		#(5);
	end
	always @(negedge clk) begin
		if (MemWrite) begin
			if ((DataAdr === 100) & (WriteData === 7)) begin
				$display("Simulation succeeded");
				$finish;
			end
			else if (DataAdr !== 96) begin
				$display("Simulation failed");
				$finish;
			end
		end
	end

	initial begin
		$dumpfile("arm.vcd");
		$dumpvars;
	end
endmodule

temp/processor/arm.vcd
$date
	Sun Dec 12 20:33:23 2021
$end
$version
	Icarus Verilog
$end
$timescale
	1s
$end
$scope module testbench $end
$var wire 32 ! WriteData [31:0] $end
$var wire 1 " MemWrite $end
$var wire 32 # DataAdr [31:0] $end
$var reg 1 $ clk $end
$var reg 1 % reset $end
$scope module dut $end
$var wire 1 $ clk $end
$var wire 1 % reset $end
$var wire 32 & WriteData [31:0] $end
$var wire 32 ' ReadData [31:0] $end
$var wire 32 ( PC [31:0] $end
$var wire 1 " MemWrite $end
$var wire 32 ) Instr [31:0] $end
$var wire 32 * DataAdr [31:0] $end
$scope module arm $end
$var wire 1 $ clk $end
$var wire 1 % reset $end
$var wire 32 + WriteData [31:0] $end
$var wire 1 , RegWrite $end
$var wire 2 - RegSrc [1:0] $end
$var wire 32 . ReadData [31:0] $end
$var wire 1 / PCSrc $end
$var wire 32 0 PC [31:0] $end
$var wire 1 1 MemtoReg $end
$var wire 1 " MemWrite $end
$var wire 32 2 Instr [31:0] $end
$var wire 2 3 ImmSrc [1:0] $end
$var wire 1 4 ALUSrc $end
$var wire 32 5 ALUResult [31:0] $end
$var wire 4 6 ALUFlags [3:0] $end
$var wire 3 7 ALUControl [2:0] $end
$scope module c $end
$var wire 20 8 Instr [31:12] $end
$var wire 1 $ clk $end
$var wire 1 % reset $end
$var wire 1 , RegWrite $end
$var wire 1 9 RegW $end
$var wire 2 : RegSrc [1:0] $end
$var wire 1 / PCSrc $end
$var wire 1 ; PCS $end
$var wire 1 1 MemtoReg $end
$var wire 1 " MemWrite $end
$var wire 1 < MemW $end
$var wire 2 = ImmSrc [1:0] $end
$var wire 2 > FlagW [1:0] $end
$var wire 1 4 ALUSrc $end
$var wire 4 ? ALUFlags [3:0] $end
$var wire 3 @ ALUControl [2:0] $end
$scope module cl $end
$var wire 4 A Cond [3:0] $end
$var wire 2 B FlagWrite [1:0] $end
$var wire 1 " MemWrite $end
$var wire 1 / PCSrc $end
$var wire 1 , RegWrite $end
$var wire 1 $ clk $end
$var wire 1 % reset $end
$var wire 1 9 RegW $end
$var wire 1 ; PCS $end
$var wire 1 < MemW $end
$var wire 4 C Flags [3:0] $end
$var wire 2 D FlagW [1:0] $end
$var wire 1 E CondEx $end
$var wire 4 F ALUFlags [3:0] $end
$scope module cc $end
$var wire 4 G Cond [3:0] $end
$var wire 4 H Flags [3:0] $end
$var wire 1 I ge $end
$var wire 1 J zero $end
$var wire 1 K overflow $end
$var wire 1 L neg $end
$var wire 1 M carry $end
$var reg 1 E CondEx $end
$upscope $end
$scope module flagreg0 $end
$var wire 1 $ clk $end
$var wire 2 N d [1:0] $end
$var wire 1 O en $end
$var wire 1 % reset $end
$var reg 2 P q [1:0] $end
$upscope $end
$scope module flagreg1 $end
$var wire 1 $ clk $end
$var wire 2 Q d [1:0] $end
$var wire 1 R en $end
$var wire 1 % reset $end
$var reg 2 S q [1:0] $end
$upscope $end
$upscope $end
$scope module dec $end
$var wire 6 T Funct [5:0] $end
$var wire 2 U Op [1:0] $end
$var wire 1 ; PCS $end
$var wire 4 V Rd [3:0] $end
$var wire 1 9 RegW $end
$var wire 2 W RegSrc [1:0] $end
$var wire 1 1 MemtoReg $end
$var wire 1 < MemW $end
$var wire 2 X ImmSrc [1:0] $end
$var wire 1 Y Branch $end
$var wire 1 4 ALUSrc $end
$var wire 1 Z ALUOp $end
$var reg 3 [ ALUControl [2:0] $end
$var reg 2 \ FlagW [1:0] $end
$var reg 10 ] controls [9:0] $end
$upscope $end
$upscope $end
$scope module dp $end
$var wire 3 ^ ALUControl [2:0] $end
$var wire 1 4 ALUSrc $end
$var wire 2 _ ImmSrc [1:0] $end
$var wire 1 1 MemtoReg $end
$var wire 1 / PCSrc $end
$var wire 2 ` RegSrc [1:0] $end
$var wire 1 , RegWrite $end
$var wire 1 $ clk $end
$var wire 1 % reset $end
$var wire 32 a WriteData [31:0] $end
$var wire 32 b SrcB [31:0] $end
$var wire 32 c SrcA [31:0] $end
$var wire 32 d Result [31:0] $end
$var wire 32 e ReadData [31:0] $end
$var wire 4 f RA2 [3:0] $end
$var wire 4 g RA1 [3:0] $end
$var wire 32 h PCPlus8 [31:0] $end
$var wire 32 i PCPlus4 [31:0] $end
$var wire 32 j PCNext [31:0] $end
$var wire 32 k PC [31:0] $end
$var wire 32 l Instr [31:0] $end
$var wire 32 m ExtImm [31:0] $end
$var wire 32 n ALUResult [31:0] $end
$var wire 4 o ALUFlags [3:0] $end
$scope module alu $end
$var wire 3 p ALUControl [2:0] $end
$var wire 1 q Carry $end
$var wire 1 r Overflow $end
$var wire 1 s Zero $end
$var wire 32 t mux2_1 [31:0] $end
$var wire 33 u Sum [32:0] $end
$var wire 64 v Product [63:0] $end
$var wire 1 w Negative $end
$var wire 32 x FactorB [31:0] $end
$var wire 32 y FactorA [31:0] $end
$var wire 32 z B [31:0] $end
$var wire 4 { ALUFlags [3:0] $end
$var wire 32 | A [31:0] $end
$var reg 32 } Result [31:0] $end
$var reg 32 ~ ResultExtra [31:0] $end
$upscope $end
$scope module ext $end
$var wire 2 !" ImmSrc [1:0] $end
$var wire 24 "" Instr [23:0] $end
$var reg 32 #" ExtImm [31:0] $end
$upscope $end
$scope module pcadd1 $end
$var wire 32 $" b [31:0] $end
$var wire 32 %" y [31:0] $end
$var wire 32 &" a [31:0] $end
$upscope $end
$scope module pcadd2 $end
$var wire 32 '" a [31:0] $end
$var wire 32 (" b [31:0] $end
$var wire 32 )" y [31:0] $end
$upscope $end
$scope module pcmux $end
$var wire 32 *" d0 [31:0] $end
$var wire 1 / s $end
$var wire 32 +" y [31:0] $end
$var wire 32 ," d1 [31:0] $end
$upscope $end
$scope module pcreg $end
$var wire 1 $ clk $end
$var wire 32 -" d [31:0] $end
$var wire 1 % reset $end
$var reg 32 ." q [31:0] $end
$upscope $end
$scope module ra1mux $end
$var wire 4 /" d0 [3:0] $end
$var wire 4 0" d1 [3:0] $end
$var wire 1 1" s $end
$var wire 4 2" y [3:0] $end
$upscope $end
$scope module ra2mux $end
$var wire 4 3" d0 [3:0] $end
$var wire 4 4" d1 [3:0] $end
$var wire 1 5" s $end
$var wire 4 6" y [3:0] $end
$upscope $end
$scope module resmux $end
$var wire 32 7" d0 [31:0] $end
$var wire 1 1 s $end
$var wire 32 8" y [31:0] $end
$var wire 32 9" d1 [31:0] $end
$upscope $end
$scope module rf $end
$var wire 1 $ clk $end
$var wire 32 :" r15 [31:0] $end
$var wire 4 ;" ra1 [3:0] $end
$var wire 4 <" ra2 [3:0] $end
$var wire 4 =" wa3 [3:0] $end
$var wire 32 >" wd3 [31:0] $end
$var wire 1 , we3 $end
$var wire 32 ?" rd2 [31:0] $end
$var wire 32 @" rd1 [31:0] $end
$upscope $end
$scope module srcbmux $end
$var wire 32 A" d0 [31:0] $end
$var wire 32 B" d1 [31:0] $end
$var wire 1 4 s $end
$var wire 32 C" y [31:0] $end
$upscope $end
$upscope $end
$upscope $end
$scope module dmem $end
$var wire 32 D" a [31:0] $end
$var wire 1 $ clk $end
$var wire 32 E" rd [31:0] $end
$var wire 32 F" wd [31:0] $end
$var wire 1 " we $end
$upscope $end
$scope module imem $end
$var wire 32 G" a [31:0] $end
$var wire 32 H" rd [31:0] $end
$upscope $end
$upscope $end
$upscope $end
$enddefinitions $end
#0
$dumpvars
b11100000010011110000000000001111 H"
b0 G"
b1000 F"
bx E"
b0 D"
b1000 C"
b1111 B"
b1000 A"
b1000 @"
b1000 ?"
b0 >"
b0 ="
b1111 <"
b1111 ;"
b1000 :"
bx 9"
b0 8"
b0 7"
b1111 6"
05"
b0 4"
b1111 3"
b1111 2"
01"
b1111 0"
b1111 /"
b0 ."
b100 -"
b0 ,"
b100 +"
b100 *"
b1000 )"
b100 ("
b100 '"
b0 &"
b100 %"
b100 $"
b1111 #"
b10011110000000000001111 ""
b0 !"
b0 ~
b0 }
b1000 |
b110 {
b1000 z
b1000 y
b1000 x
0w
b1000000 v
b100000000000000000000000000000000 u
b11111111111111111111111111110111 t
1s
0r
1q
b1 p
b110 o
b0 n
b1111 m
b11100000010011110000000000001111 l
b0 k
b100 j
b100 i
b1000 h
b1111 g
b1111 f
bx e
b0 d
b1000 c
b1000 b
b1000 a
b0 `
b0 _
b1 ^
b1001 ]
b0 \
b1 [
1Z
0Y
b0 X
b0 W
b0 V
b0 U
b100 T
b0 S
0R
b1 Q
b0 P
0O
b10 N
0M
0L
0K
0J
1I
b0 H
b1110 G
b110 F
1E
b0 D
b0 C
b0 B
b1110 A
b1 @
b110 ?
b0 >
b0 =
0<
0;
b0 :
19
b11100000010011110000 8
b1 7
b110 6
b0 5
04
b0 3
b11100000010011110000000000001111 2
01
b0 0
0/
bx .
b0 -
1,
b1000 +
b0 *
b11100000010011110000000000001111 )
b0 (
bx '
b1000 &
1%
1$
b0 #
0"
b1000 !
$end
#5
0$
#10
1$
#15
0$
#20
1$
#22
0%
#25
0$
#30
b0 N
0w
0q
14
b0 7
b0 @
b0 [
b0 ^
b0 p
b101001 ]
b0 Q
b101 t
b101 m
b101 #"
b101 B"
b101 f
b101 6"
b101 <"
b0 g
b0 2"
b0 ;"
b101000 T
b10 V
b0 v
b0 6
b0 ?
b0 F
b0 o
b0 {
0s
b101 d
b101 ,"
b101 8"
b101 >"
b101 x
b100000000010000000000101 ""
b10 ="
b10 4"
b101 3"
b0 /"
b11100010100000000010 8
b0 y
b101 #
b101 *
b101 5
b101 n
b101 }
b101 7"
b101 D"
b101 b
b101 z
b101 C"
b11100010100000000010000000000101 )
b11100010100000000010000000000101 2
b11100010100000000010000000000101 l
b11100010100000000010000000000101 H"
b101 u
b0 c
b0 |
b0 @"
bx !
bx &
bx +
bx a
bx ?"
bx A"
bx F"
b1000 j
b1000 +"
b1000 -"
b1100 h
b1100 )"
b1100 :"
b1000 i
b1000 %"
b1000 '"
b1000 *"
b100 (
b100 0
b100 k
b100 &"
b100 ."
b100 G"
1$
#35
0$
#40
b1100 d
b1100 ,"
b1100 8"
b1100 >"
b1100 #
b1100 *
b1100 5
b1100 n
b1100 }
b1100 7"
b1100 D"
b1100 x
b1100 u
b1100 t
b1100 b
b1100 z
b1100 C"
b1100 m
b1100 #"
b1100 B"
b1100 f
b1100 6"
b1100 <"
b11 V
b100000000011000000001100 ""
b11 ="
b11 4"
b1100 3"
b11100010100000000011 8
b11100010100000000011000000001100 )
b11100010100000000011000000001100 2
b11100010100000000011000000001100 l
b11100010100000000011000000001100 H"
b1100 j
b1100 +"
b1100 -"
b10000 h
b10000 )"
b10000 :"
b1100 i
b1100 %"
b1100 '"
b1100 *"
b1000 (
b1000 0
b1000 k
b1000 &"
b1000 ."
b1000 G"
1$
#45
0$
#50
b10 N
b10 6
b10 ?
b10 F
b10 o
b10 {
1q
b1101100 v
b11 d
b11 ,"
b11 8"
b11 >"
b1001 x
b11111111111111111111111111110110 t
b1100 y
b11 #
b11 *
b11 5
b11 n
b11 }
b11 7"
b11 D"
b1001 b
b1001 z
b1001 C"
b100000000000000000000000000000011 u
b1100 c
b1100 |
b1100 @"
b1 7
b1 @
b1 [
b1 ^
b1 p
b1001 m
b1001 #"
b1001 B"
b1001 f
b1001 6"
b1001 <"
b11 g
b11 2"
b11 ;"
b100100 T
b111 V
b10000110111000000001001 ""
b111 ="
b111 4"
b1001 3"
b11 /"
b11100010010000110111 8
b11100010010000110111000000001001 )
b11100010010000110111000000001001 2
b11100010010000110111000000001001 l
b11100010010000110111000000001001 H"
b10000 j
b10000 +"
b10000 -"
b10100 h
b10100 )"
b10100 :"
b10000 i
b10000 %"
b10000 '"
b10000 *"
b1100 (
b1100 0
b1100 k
b1100 &"
b1100 ."
b1100 G"
1$
#55
0$
#60
b111 d
b111 ,"
b111 8"
b111 >"
b0 N
b111 #
b111 *
b111 5
b111 n
b111 }
b111 7"
b111 D"
b11111111111111111111111111111010 t
b1111 v
b0 6
b0 ?
b0 F
b0 o
b0 {
0q
b101 x
b11 y
04
b101 b
b101 z
b101 C"
b101 !
b101 &
b101 +
b101 a
b101 ?"
b101 A"
b101 F"
b11111111111111111111111111111110 u
b11 c
b11 |
b11 @"
b11 7
b11 @
b11 [
b11 ^
b11 p
b1001 ]
b10 m
b10 #"
b10 B"
b10 f
b10 6"
b10 <"
b111 g
b111 2"
b111 ;"
b11000 T
b100 V
b100001110100000000000010 ""
b100 ="
b100 4"
b10 3"
b111 /"
b11100001100001110100 8
b11100001100001110100000000000010 )
b11100001100001110100000000000010 2
b11100001100001110100000000000010 l
b11100001100001110100000000000010 H"
b10100 j
b10100 +"
b10100 -"
b11000 h
b11000 )"
b11000 :"
b10100 i
b10100 %"
b10100 '"
b10100 *"
b10000 (
b10000 0
b10000 k
b10000 &"
b10000 ."
b10000 G"
1$
#65
0$
#70
b111 x
b1010100 v
b100 d
b100 ,"
b100 8"
b100 >"
b111 t
b111 b
b111 z
b111 C"
b1100 y
b100 #
b100 *
b100 5
b100 n
b100 }
b100 7"
b100 D"
b111 !
b111 &
b111 +
b111 a
b111 ?"
b111 A"
b111 F"
b10011 u
b1100 c
b1100 |
b1100 @"
b10 7
b10 @
b10 [
b10 ^
b10 p
b100 m
b100 #"
b100 B"
b100 f
b100 6"
b100 <"
b11 g
b11 2"
b11 ;"
b0 T
b101 V
b110101000000000100 ""
b101 ="
b101 4"
b100 3"
b11 /"
b11100000000000110101 8
b11100000000000110101000000000100 )
b11100000000000110101000000000100 2
b11100000000000110101000000000100 l
b11100000000000110101000000000100 H"
b11000 j
b11000 +"
b11000 -"
b11100 h
b11100 )"
b11100 :"
b11000 i
b11000 %"
b11000 '"
b11000 *"
b10100 (
b10100 0
b10100 k
b10100 &"
b10100 ."
b10100 G"
1$
#75
0$
#80
b11100 v
b1011 d
b1011 ,"
b1011 8"
b1011 >"
b100 y
b1011 #
b1011 *
b1011 5
b1011 n
b1011 }
b1011 7"
b1011 D"
b1011 u
b100 c
b100 |
b100 @"
b0 7
b0 @
b0 [
b0 ^
b0 p
b101 g
b101 2"
b101 ;"
b1000 T
b100001010101000000000100 ""
b101 /"
b11100000100001010101 8
b11100000100001010101000000000100 )
b11100000100001010101000000000100 2
b11100000100001010101000000000100 l
b11100000100001010101000000000100 H"
b11100 j
b11100 +"
b11100 -"
b100000 h
b100000 )"
b100000 :"
b11100 i
b11100 %"
b11100 '"
b11100 *"
b11000 (
b11000 0
b11000 k
b11000 &"
b11000 ."
b11000 G"
1$
#85
0$
#90
b10 N
b10 6
b10 ?
b10 F
b10 o
b10 {
1q
b11 x
1R
1O
b11111111111111111111111111111100 t
b11 b
b11 z
b11 C"
b11 B
b11 !
b11 &
b11 +
b11 a
b11 ?"
b11 A"
b11 F"
b11 >
b11 D
b11 \
b1 7
b1 @
b1 [
b1 ^
b1 p
b111 m
b111 #"
b111 B"
b111 f
b111 6"
b111 <"
b101 T
b1000 V
b100001 v
b1000 d
b1000 ,"
b1000 8"
b1000 >"
b10101011000000000000111 ""
b1000 ="
b1000 4"
b111 3"
b11100000010101011000 8
b1011 y
b1000 #
b1000 *
b1000 5
b1000 n
b1000 }
b1000 7"
b1000 D"
b11100000010101011000000000000111 )
b11100000010101011000000000000111 2
b11100000010101011000000000000111 l
b11100000010101011000000000000111 H"
b100000 j
b100000 +"
b100000 -"
b100000000000000000000000000001000 u
b1011 c
b1011 |
b1011 @"
b100100 h
b100100 )"
b100100 :"
b100000 i
b100000 %"
b100000 '"
b100000 *"
b11100 (
b11100 0
b11100 k
b11100 &"
b11100 ."
b11100 G"
1$
#95
0$
